pycpp_tools/__init__.py
pycpp_tools/configure.py
pycpp_tools/default.toml
pycpp_tools/general.py
pycpp_tools/pybind11.py
pycpp_tools/script.py
pycpp_tools/vscode.py
pycpp_tools-0.2.4.dist-info/METADATA
pycpp_tools-0.2.4.dist-info/WHEEL
pycpp_tools-0.2.4.dist-info/entry_points.txt
pycpp_tools-0.2.4.dist-info/top_level.txt
pycpp_tools-0.2.4.dist-info/RECORD
