Metadata-Version: 2.4
Name: pycpp_tools
Version: 0.2.4
Summary: A utility library to assist Pybind11 projects.
Author-email: "R.E." <redelephant@foxmail.com>
License: MIT
Classifier: Development Status :: 3 - Alpha
Classifier: Intended Audience :: Developers
Classifier: Programming Language :: Python :: 3
Classifier: Programming Language :: Python :: 3.8
Classifier: Programming Language :: Python :: 3.9
Classifier: Programming Language :: Python :: 3.10
Classifier: Programming Language :: Python :: 3.11
Classifier: Programming Language :: Python :: 3.12
Classifier: Programming Language :: Python :: 3.13
Classifier: Programming Language :: Python :: 3.14
Requires-Python: >=3.8
Requires-Dist: tomli_w
Requires-Dist: pydantic
Requires-Dist: pyjson5
Requires-Dist: pybind11
